dreamai_pdf/__init__.py
dreamai_pdf/_modidx.py
dreamai_pdf/core.py
dreamai_pdf/extract.py
dreamai_pdf/imports.py
dreamai_pdf/ner.py
dreamai_pdf-0.1.2.dist-info/LICENSE
dreamai_pdf-0.1.2.dist-info/METADATA
dreamai_pdf-0.1.2.dist-info/WHEEL
dreamai_pdf-0.1.2.dist-info/entry_points.txt
dreamai_pdf-0.1.2.dist-info/top_level.txt
dreamai_pdf-0.1.2.dist-info/RECORD
