Metadata-Version: 2.1
Name: dreamai-pdf
Version: 0.1.2
Summary: Library based on DreamAI for parsing PDFs
Home-page: https://github.com/HamzaFarhan/dreamai_pdf
Author: Hamza Farhan
Author-email: thehamza96@gmail.com
License: Apache Software License 2.0
Keywords: nbdev jupyter notebook python
Classifier: Development Status :: 4 - Beta
Classifier: Intended Audience :: Developers
Classifier: Natural Language :: English
Classifier: Programming Language :: Python :: 3.7
Classifier: Programming Language :: Python :: 3.8
Classifier: Programming Language :: Python :: 3.9
Classifier: Programming Language :: Python :: 3.10
Classifier: License :: OSI Approved :: Apache Software License
Requires-Python: >=3.7
License-File: LICENSE
Requires-Dist: dreamai
Requires-Dist: dreamai-dl
Requires-Dist: pypdf
Requires-Dist: sentence-transformers
Requires-Dist: setfit
Requires-Dist: setuptools
Provides-Extra: dev
